jupyter_events/__init__.py
jupyter_events/_version.py
jupyter_events/cli.py
jupyter_events/logger.py
jupyter_events/py.typed
jupyter_events/pytest_plugin.py
jupyter_events/schema.py
jupyter_events/schema_registry.py
jupyter_events/traits.py
jupyter_events/validators.py
jupyter_events/yaml.py
jupyter_events/schemas/event-core-schema.yml
jupyter_events/schemas/event-metaschema.yml
jupyter_events/schemas/property-metaschema.yml
jupyter_events-0.10.0.dist-info/METADATA
jupyter_events-0.10.0.dist-info/WHEEL
jupyter_events-0.10.0.dist-info/entry_points.txt
jupyter_events-0.10.0.dist-info/licenses/LICENSE
jupyter_events-0.10.0.dist-info/RECORD
