Metadata-Version: 2.3
Name: jupyter-events
Version: 0.10.0
Summary: Jupyter Event System library
Project-URL: Homepage, http://jupyter.org
Project-URL: documentation, https://jupyter-events.readthedocs.io/
Project-URL: repository, https://github.com/jupyter/jupyter_events.git
Project-URL: changelog, https://github.com/jupyter/jupyter_events/blob/main/CHANGELOG.md
Author-email: Jupyter Development Team <jupyter@googlegroups.com>
License: BSD 3-Clause License
License-File: LICENSE
Keywords: Jupyter,JupyterLab
Classifier: Intended Audience :: Developers
Classifier: Intended Audience :: Science/Research
Classifier: Intended Audience :: System Administrators
Classifier: License :: OSI Approved :: BSD License
Classifier: Programming Language :: Python
Classifier: Programming Language :: Python :: 3
Requires-Python: >=3.8
Requires-Dist: jsonschema[format-nongpl]>=4.18.0
Requires-Dist: python-json-logger>=2.0.4
Requires-Dist: pyyaml>=5.3
Requires-Dist: referencing
Requires-Dist: rfc3339-validator
Requires-Dist: rfc3986-validator>=0.1.1
Requires-Dist: traitlets>=5.3
Provides-Extra: cli
Requires-Dist: click; extra == 'cli'
Requires-Dist: rich; extra == 'cli'
Provides-Extra: docs
Requires-Dist: jupyterlite-sphinx; extra == 'docs'
Requires-Dist: myst-parser; extra == 'docs'
Requires-Dist: pydata-sphinx-theme; extra == 'docs'
Requires-Dist: sphinxcontrib-spelling; extra == 'docs'
Provides-Extra: test
Requires-Dist: click; extra == 'test'
Requires-Dist: pre-commit; extra == 'test'
Requires-Dist: pytest-asyncio>=0.19.0; extra == 'test'
Requires-Dist: pytest-console-scripts; extra == 'test'
Requires-Dist: pytest>=7.0; extra == 'test'
Requires-Dist: rich; extra == 'test'
